{"__symbolic":"module","version":4,"metadata":{"CdkTableExporterModule":{"__symbolic":"class","decorators":[{"__symbolic":"call","expression":{"__symbolic":"reference","module":"@angular/core","name":"NgModule","line":2,"character":1},"arguments":[{"declarations":[],"imports":[],"exports":[]}]}],"members":{}},"CdkTableExporter":{"__symbolic":"class","members":{"cdkTable":[{"__symbolic":"property","decorators":[{"__symbolic":"call","expression":{"__symbolic":"reference","module":"@angular/core","name":"Input","line":10,"character":3}}]}],"exporterButton":[{"__symbolic":"property","decorators":[{"__symbolic":"call","expression":{"__symbolic":"reference","module":"@angular/core","name":"Input","line":11,"character":3}}]}],"sheetName":[{"__symbolic":"property","decorators":[{"__symbolic":"call","expression":{"__symbolic":"reference","module":"@angular/core","name":"Input","line":12,"character":3}}]}],"fileName":[{"__symbolic":"property","decorators":[{"__symbolic":"call","expression":{"__symbolic":"reference","module":"@angular/core","name":"Input","line":13,"character":3}}]}],"hiddenColumns":[{"__symbolic":"property","decorators":[{"__symbolic":"call","expression":{"__symbolic":"reference","module":"@angular/core","name":"Input","line":14,"character":3}}]}],"exportCompleted":[{"__symbolic":"property","decorators":[{"__symbolic":"call","expression":{"__symbolic":"reference","module":"@angular/core","name":"Output","line":15,"character":3}}]}],"exportStarted":[{"__symbolic":"property","decorators":[{"__symbolic":"call","expression":{"__symbolic":"reference","module":"@angular/core","name":"Output","line":16,"character":3}}]}],"__ctor__":[{"__symbolic":"constructor","parameters":[{"__symbolic":"reference","module":"@angular/core","name":"Renderer2","line":29,"character":34},{"__symbolic":"reference","name":"JsonExporterService"}]}],"getPageCount":[{"__symbolic":"method"}],"getCurrentPageIndex":[{"__symbolic":"method"}],"goToPage":[{"__symbolic":"method"}],"getPageChangeObservable":[{"__symbolic":"method"}],"ngAfterViewInit":[{"__symbolic":"method"}],"exportTable":[{"__symbolic":"method"}],"exportWithPagination":[{"__symbolic":"method"}],"exportSinglePage":[{"__symbolic":"method"}],"extractDataOnCurrentPage":[{"__symbolic":"method"}],"initPageHandler":[{"__symbolic":"method"}],"exportExtractedData":[{"__symbolic":"method"}],"extractExcelRows":[{"__symbolic":"method"}],"extractExcelHeaderRow":[{"__symbolic":"method"}],"getRenderedRows":[{"__symbolic":"method"}],"convertToJsonArray":[{"__symbolic":"method"}],"convertRow":[{"__symbolic":"method"}],"shouldHide":[{"__symbolic":"method"}],"customizeRow":[{"__symbolic":"method"}],"createExcelItem":[{"__symbolic":"method"}],"hasNextPage":[{"__symbolic":"method"}],"nextPage":[{"__symbolic":"method"}],"enableExportButton":[{"__symbolic":"method"}]}},"JsonExporterService":{"__symbolic":"class","decorators":[{"__symbolic":"call","expression":{"__symbolic":"reference","module":"@angular/core","name":"Injectable","line":3,"character":1},"arguments":[{"providedIn":"root"}]}],"members":{"__ctor__":[{"__symbolic":"constructor"}],"exportExcel":[{"__symbolic":"method"}],"hideColumns":[{"__symbolic":"method"}],"appendExtensionIfNotProvided":[{"__symbolic":"method"}]},"statics":{"ngInjectableDef":{}}}},"origins":{"CdkTableExporterModule":"./lib/cdk-table-exporter.module","CdkTableExporter":"./lib/cdk-table-exporter","JsonExporterService":"./lib/json-exporter.service"},"importAs":"cdk-table-exporter"}